MANIFEST.in
README.rst
setup.cfg
setup.py
mercadopago/__init__.py
mercadopago/abstract_api.py
mercadopago/api.py
mercadopago/client.py
mercadopago/errors.py
mercadopago/response.py
pymercadopago.egg-info/PKG-INFO
pymercadopago.egg-info/SOURCES.txt
pymercadopago.egg-info/dependency_links.txt
pymercadopago.egg-info/requires.txt
pymercadopago.egg-info/top_level.txt