Metadata-Version: 1.1
Name: pymercadopago
Version: 0.3.0
Summary: An API wrapper for MercadoPago
Home-page: https://github.com/federicobond/pymercadopago
Author: Federico Bond
Author-email: federicobond@gmail.com
License: Apache 2.0
Keywords: mercadopago api
Platform: UNKNOWN
Classifier: Development Status :: 4 - Beta
Classifier: Intended Audience :: Developers
Classifier: Topic :: Internet :: WWW/HTTP
Classifier: License :: OSI Approved :: Apache Software License
Classifier: Programming Language :: Python :: 3
Classifier: Programming Language :: Python :: 3.6
Classifier: Programming Language :: Python :: 3.7
